<?xml version="1.0" encoding="UTF-8"?>
<feature
      id="com.perforce.team.charts.feature"
      label="Perforce Charting Support (BIRT Prerequisite)"
      version="11.1.1.qualifier"
      provider-name="Perforce Software"
      plugin="com.perforce.team.branding">

   <description>
      This feature contains the P4Eclipse Charting plug-in.
   </description>

   <license>
      P4Eclipse is part of Perforce, The Fast Software Configuration Management System.  
For server downloads and licensing, see www.perforce.com/download.html.
   </license>

   <requires>
      <import feature="com.perforce.team.feature" version="0.0.0" match="greaterOrEqual"/>
      <import feature="org.eclipse.birt" version="2.6.2" match="greaterOrEqual"/>
      <import plugin="org.eclipse.ui"/>
      <import plugin="org.eclipse.core.runtime"/>
      <import plugin="com.perforce.team.core"/>
      <import plugin="com.perforce.team.ui"/>
      <import plugin="com.perforce.team.ui.text"/>
      <import plugin="org.eclipse.jface.text"/>
      <import plugin="org.eclipse.ui.editors"/>
      <import plugin="org.eclipse.team.core"/>
      <import plugin="org.eclipse.ui.forms"/>
   </requires>

   <plugin
         id="com.perforce.team.ui.charts"
         download-size="0"
         install-size="0"
         version="0.0.0"
         unpack="false"/>

</feature>
